setup.py
sereh/__init__.py
sereh/__version__.py
sereh/commandline.py
sereh/subexception.py
sereh/subfile.py
sereh/subitem.py
sereh/subtime.py
sereh.egg-info/PKG-INFO
sereh.egg-info/SOURCES.txt
sereh.egg-info/dependency_links.txt
sereh.egg-info/entry_points.txt
sereh.egg-info/not-zip-safe
sereh.egg-info/requires.txt
sereh.egg-info/top_level.txt